fast_demo.cpython-38-x86_64-linux-gnu.so
fast_demo.libs/libgcc_s-2298274a.so.1
fast_demo.libs/libstdc++-08d5c7eb.so.6.0.33
fast_demo-3.8.dist-info/METADATA
fast_demo-3.8.dist-info/WHEEL
fast_demo-3.8.dist-info/top_level.txt
fast_demo-3.8.dist-info/RECORD
