Metadata-Version: 2.1
Name: fast-demo
Version: 3.8
Summary: Encrypted ODOO module
Author-email: RoyZ <2820003660@qq.com>
License: GPL-3.0-or-later
Platform: any
Requires-Python: >=3.7
Requires-Dist: pybind11>=2.6.0
